gimli/errors.py
gimli/units.py
gimli/_constants.py
gimli/_main.py
gimli/_system.py
gimli/_udunits2.cp313-win_amd64.pyd
gimli/_udunits2.pyx
gimli/_utils.py
gimli/_version.py
gimli/__init__.py
gimli/__main__.py
gimli/data/udunits/udunits2-accepted.xml
gimli/data/udunits/udunits2-accepted.xml.nonCF
gimli/data/udunits/udunits2-base.xml
gimli/data/udunits/udunits2-common.xml
gimli/data/udunits/udunits2-common.xml.nonCF
gimli/data/udunits/udunits2-derived.xml
gimli/data/udunits/udunits2-derived.xml.nonCF
gimli/data/udunits/udunits2-prefixes.xml
gimli/data/udunits/udunits2.xml
gimli.units-0.3.3.dist-info/AUTHORS.md
gimli.units-0.3.3.dist-info/DELVEWHEEL
gimli.units-0.3.3.dist-info/entry_points.txt
gimli.units-0.3.3.dist-info/LICENSE.md
gimli.units-0.3.3.dist-info/METADATA
gimli.units-0.3.3.dist-info/RECORD
gimli.units-0.3.3.dist-info/top_level.txt
gimli.units-0.3.3.dist-info/WHEEL
gimli.units.libs/libexpat-afdf62075ac7ce6c0af046b648e5da4e.dll
gimli.units.libs/udunits2-3ac2c4c1f8fd8d3e3e962e1cf6664e21.dll
