Metadata-Version: 2.1
Name: gimli.units
Version: 0.3.3
Summary: An object-oriented Python interface to udunits
Author: Eric Hutton
Author-email: eric.hutton@colorado.edu
Maintainer: Eric Hutton
Maintainer-email: eric.hutton@colorado.edu
License: MIT
Project-URL: Changelog, https://github.com/csdms/gimli/blob/master/CHANGES.rst
Project-URL: Documentation, https://gimli.readthedocs.io/
Project-URL: Homepage, https://github.com/csdms/gimli
Project-URL: Repository, https://github.com/csdms/gimli
Keywords: earth science,model coupling,unit conversion,units
Classifier: Development Status :: 4 - Beta
Classifier: Intended Audience :: Science/Research
Classifier: License :: OSI Approved :: MIT License
Classifier: Operating System :: OS Independent
Classifier: Programming Language :: Python :: 3
Classifier: Programming Language :: Python :: 3.10
Classifier: Programming Language :: Python :: 3.11
Classifier: Programming Language :: Python :: 3.12
Classifier: Topic :: Scientific/Engineering :: Physics
Requires-Python: >=3.10
License-File: LICENSE.md
License-File: AUTHORS.md
Requires-Dist: numpy
Requires-Dist: importlib-resources; python_version < "3.12"
Provides-Extra: dev
Requires-Dist: nox; extra == "dev"
Provides-Extra: testing
Requires-Dist: hypothesis; extra == "testing"
Requires-Dist: pytest; extra == "testing"
Requires-Dist: pytest-cov; extra == "testing"
